cSED.cpython-36m-x86_64-linux-gnu.so
cSED-1.0.dist-info/top_level.txt
cSED-1.0.dist-info/RECORD
cSED-1.0.dist-info/WHEEL
cSED-1.0.dist-info/METADATA
