Metadata-Version: 2.1
Name: cSED
Version: 1.0
Summary: substring edit distance by c
Home-page: UNKNOWN
Author: sykwon
Author-email: sykwon@kdd.snu.ac.kr
License: MIT
Platform: UNKNOWN
Classifier: Programming Language :: Python :: 3.6
Classifier: Programming Language :: Python :: 3.7
